minswap/__init__.py
minswap/addr.py
minswap/assets.py
minswap/models/__init__.py
minswap/models/blockfrost_models.py
minswap/models/common.py
minswap/pools.py
minswap/transactions.py
minswap/utils.py
minswap/wallets.py
minswap_py-0.3.5.dist-info/LICENSE
minswap_py-0.3.5.dist-info/METADATA
minswap_py-0.3.5.dist-info/WHEEL
minswap_py-0.3.5.dist-info/RECORD
