Metadata-Version: 2.1
Name: minswap-py
Version: 0.3.5
Summary: 
Home-page: https://github.com/theeldermillenial/minswap-py
License: MIT
Author: eldermillenial
Author-email: eldermillenial@protonmail.com
Requires-Python: >=3.8.1,<4.0.0
Classifier: License :: OSI Approved :: MIT License
Classifier: Programming Language :: Python :: 3
Classifier: Programming Language :: Python :: 3.9
Classifier: Programming Language :: Python :: 3.10
Classifier: Programming Language :: Python :: 3.11
Classifier: Programming Language :: Python :: 3.12
Requires-Dist: blockfrost-python (==0.5.3)
Requires-Dist: numba (>=0.56.4,<0.57.0)
Requires-Dist: pycardano (==0.9.0)
Requires-Dist: pydantic (==2.5.2)
Requires-Dist: python-dotenv (==0.21.1)
Requires-Dist: tqdm (>=4.65.0,<5.0.0)
Requires-Dist: vaex-core (>=4.17.1,<5.0.0)
Project-URL: Issues, https://github.com/theeldermillenial/minswap-py/issues
Project-URL: Repository, https://github.com/theeldermillenial/minswap-py
